callsign_regex/__init__.py
callsign_regex/__main__.py
callsign_regex/callsign_regex.py
itu_appendix42/__init__.py
itu_appendix42/iso3661_mapping.py
itu_appendix42/iso3661_mapping_from_itu.py
itu_appendix42/itu_appendix42.py
itu_appendix42/log.py
itu_appendix42/worksheet.py
itu_appendix42/resources/CallSignSeriesRanges-00000000-0000-0000-0000-000000000000.xlsx
callsign_regex-0.7.1.dist-info/LICENSE
callsign_regex-0.7.1.dist-info/METADATA
callsign_regex-0.7.1.dist-info/WHEEL
callsign_regex-0.7.1.dist-info/entry_points.txt
callsign_regex-0.7.1.dist-info/top_level.txt
callsign_regex-0.7.1.dist-info/RECORD
