Metadata-Version: 2.1
Name: callsign-regex
Version: 0.7.1
Summary: Match ham radio callsigns based on ITU appendix42
Home-page: https://github.com/mahtin/callsign-regex
Download-URL: https://github.com/mahtin/callsign-regex/archive/refs/tags/0.7.1.tar.gz
Author: Martin J Levy
Author-email: mahtin@mahtin.com
License: OSI Approved :: MIT License
Keywords: Ham Radio,Callsign,ITU,Appendix42
Classifier: Development Status :: 4 - Beta
Classifier: Intended Audience :: Developers
Classifier: Intended Audience :: System Administrators
Classifier: Topic :: Communications :: Ham Radio
Classifier: License :: OSI Approved :: MIT License
Classifier: Programming Language :: Python :: 3
Requires-Python: >=3.7
License-File: LICENSE
Requires-Dist: openpyxl
